Metadata-Version: 2.1
Name: spnr
Version: 0.2.1
Summary: A command line toolset
Home-page: https://github.com/suransea/spanner
Author: sea
Author-email: simpleslight@icloud.com
License: Apache-2.0
Platform: UNKNOWN
Classifier: Programming Language :: Python :: 3
Classifier: License :: OSI Approved :: Apache Software License
